README.rst
setup.cfg
setup.py
pInteServ.egg-info/PKG-INFO
pInteServ.egg-info/SOURCES.txt
pInteServ.egg-info/dependency_links.txt
pInteServ.egg-info/entry_points.txt
pInteServ.egg-info/requires.txt
pInteServ.egg-info/top_level.txt
pytp/__init__.py
pytp/client_cli.py
pytp/connectsession.py
pytp/server.py
pytp/utils.py