Metadata-Version: 1.1
Name: pInteServ
Version: 0.131
Summary: Module and cli for client/server directory sync.
Home-page: https://github.com/paulcrook726/PiCloud.git
Author: Paul Crook
Author-email: paulcrook726@gmail.com
License: GNU
Platform: UNKNOWN
Classifier: Development Status :: 3 - Alpha
Classifier: Programming Language :: Python :: 3.5
Classifier: Topic :: Internet :: File Transfer Protocol (FTP)
